[
  {
    "path": "../snd/bass_01.ogg",
    "key": "bass_01",
    "class": "bB0",
    "looping": "true",
    "playing": "false",
    "img": "img/BoardButton.png"
  },
  {
    "path": "../snd/bass_02.ogg",
    "key": "bass_02",
    "class": "bB1",
    "looping": "true",
    "playing": "false",
    "img": "img/BoardButton2.png"
  },
  {
    "path": "../snd/bass_03.ogg",
    "key": "bass_03",
    "class": "bB2",
    "looping": "true",
    "playing": "false",
    "img": "img/BoardButton.png"
  },
  {
    "path": "../snd/bass_04.ogg",
    "key": "bass_04",
    "class": "bB3",
    "looping": "true",
    "playing": "false",
    "img": "img/BoardButton2.png"
  },
  {
    "path": "../snd/beat_01.ogg",
    "key": "beat_01",
    "class": "bB4",
    "looping": "true",
    "playing": "false",
    "img": "img/BoardButton.png"
  },
  {
    "path": "../snd/synth_01.ogg",
    "key": "synth_01",
    "class": "bB5",
    "looping": "true",
    "playing": "false",
    "img": "img/BoardButton2.png"
  },
  {
    "path": "../snd/synth_02.ogg",
    "key": "synth_02",
    "class": "bB5",
    "looping": "true",
    "playing": "false",
    "img": "img/BoardButton2.png"
  },
  {
    "path": "../snd/synth_03.ogg",
    "key": "synth_03",
    "class": "bB6",
    "looping": "true",
    "playing": "false",
    "img": "img/BoardButton.png"
  },
  {
    "path": "../snd/synth_04.ogg",
    "key": "synth_04",
    "class": "bB7",
    "looping": "true",
    "playing": "false",
    "img": "img/BoardButton2.png"
  }
]
